pystock_hts/Daishin.py
pystock_hts/Kiwoom.py
pystock_hts/Util.py
pystock_hts/__init__.py
pystock_hts-0.1.5.dist-info/METADATA
pystock_hts-0.1.5.dist-info/WHEEL
pystock_hts-0.1.5.dist-info/top_level.txt
pystock_hts-0.1.5.dist-info/RECORD
